invenio_accounts_rest/__init__.py
invenio_accounts_rest/config.py
invenio_accounts_rest/errors.py
invenio_accounts_rest/ext.py
invenio_accounts_rest/loaders.py
invenio_accounts_rest/proxies.py
invenio_accounts_rest/serializers.py
invenio_accounts_rest/utils.py
invenio_accounts_rest/version.py
invenio_accounts_rest/views.py
invenio_accounts_rest-1.0.0a4.dist-info/top_level.txt
invenio_accounts_rest-1.0.0a4.dist-info/entry_points.txt
invenio_accounts_rest-1.0.0a4.dist-info/METADATA
invenio_accounts_rest-1.0.0a4.dist-info/DESCRIPTION.rst
invenio_accounts_rest-1.0.0a4.dist-info/metadata.json
invenio_accounts_rest-1.0.0a4.dist-info/WHEEL
invenio_accounts_rest-1.0.0a4.dist-info/RECORD
