Metadata-Version: 2.0
Name: invenio-accounts-rest
Version: 1.0.0a4
Summary: Invenio modules that adds accounts REST API.
Home-page: https://github.com/inveniosoftware/invenio-accounts-rest
Author: CERN
Author-email: info@inveniosoftware.org
License: GPLv2
Keywords: invenio accounts REST
Platform: any
Classifier: Environment :: Web Environment
Classifier: Intended Audience :: Developers
Classifier: License :: OSI Approved :: GNU General Public License v2 (GPLv2)
Classifier: Operating System :: OS Independent
Classifier: Programming Language :: Python
Classifier: Topic :: Internet :: WWW/HTTP :: Dynamic Content
Classifier: Topic :: Software Development :: Libraries :: Python Modules
Classifier: Programming Language :: Python :: 2
Classifier: Programming Language :: Python :: 2.7
Classifier: Programming Language :: Python :: 3
Classifier: Programming Language :: Python :: 3.5
Classifier: Development Status :: 3 - Alpha
Requires-Dist: invenio-accounts (>=1.0.0b9)
Requires-Dist: invenio-db (<1.1.0,>=1.0.0b3)
Requires-Dist: invenio-rest (>=1.0.0a10)
Requires-Dist: invenio-access (>=1.0.0a11)
Requires-Dist: invenio-oauth2server (>=1.0.0a12)
Provides-Extra: all
Requires-Dist: Sphinx (>=1.4.2); extra == 'all'
Requires-Dist: check-manifest (>=0.25); extra == 'all'
Requires-Dist: coverage (>=4.0); extra == 'all'
Requires-Dist: isort (>=4.2.2); extra == 'all'
Requires-Dist: pydocstyle (>=1.0.0); extra == 'all'
Requires-Dist: pytest-cache (>=1.0); extra == 'all'
Requires-Dist: pytest-cov (>=1.8.0); extra == 'all'
Requires-Dist: pytest-pep8 (>=1.0.6); extra == 'all'
Requires-Dist: pytest (>=2.8.0); extra == 'all'
Requires-Dist: Flask-Testing; extra == 'all'
Requires-Dist: mock; extra == 'all'
Requires-Dist: jsonpatch; extra == 'all'
Requires-Dist: responses (>=0.5.1); extra == 'all'
Requires-Dist: invenio-userprofiles (>=1.0.0a9); extra == 'all'
Requires-Dist: Sphinx (>=1.4.2); extra == 'all'
Requires-Dist: check-manifest (>=0.25); extra == 'all'
Requires-Dist: coverage (>=4.0); extra == 'all'
Requires-Dist: isort (>=4.2.2); extra == 'all'
Requires-Dist: pydocstyle (>=1.0.0); extra == 'all'
Requires-Dist: pytest-cache (>=1.0); extra == 'all'
Requires-Dist: pytest-cov (>=1.8.0); extra == 'all'
Requires-Dist: pytest-pep8 (>=1.0.6); extra == 'all'
Requires-Dist: pytest (>=2.8.0); extra == 'all'
Requires-Dist: Flask-Testing; extra == 'all'
Requires-Dist: mock; extra == 'all'
Requires-Dist: jsonpatch; extra == 'all'
Requires-Dist: responses (>=0.5.1); extra == 'all'
Requires-Dist: invenio-userprofiles (>=1.0.0a9); extra == 'all'
Provides-Extra: docs
Requires-Dist: Sphinx (>=1.4.2); extra == 'docs'
Provides-Extra: tests
Requires-Dist: check-manifest (>=0.25); extra == 'tests'
Requires-Dist: coverage (>=4.0); extra == 'tests'
Requires-Dist: isort (>=4.2.2); extra == 'tests'
Requires-Dist: pydocstyle (>=1.0.0); extra == 'tests'
Requires-Dist: pytest-cache (>=1.0); extra == 'tests'
Requires-Dist: pytest-cov (>=1.8.0); extra == 'tests'
Requires-Dist: pytest-pep8 (>=1.0.6); extra == 'tests'
Requires-Dist: pytest (>=2.8.0); extra == 'tests'
Requires-Dist: Flask-Testing; extra == 'tests'
Requires-Dist: mock; extra == 'tests'
Requires-Dist: jsonpatch; extra == 'tests'
Requires-Dist: responses (>=0.5.1); extra == 'tests'
Provides-Extra: userprofiles
Requires-Dist: invenio-userprofiles (>=1.0.0a9); extra == 'userprofiles'
